pyinstrument_cext.cpython-38-x86_64-linux-gnu.so
pyinstrument_cext-0.2.4.dist-info/LICENSE
pyinstrument_cext-0.2.4.dist-info/METADATA
pyinstrument_cext-0.2.4.dist-info/top_level.txt
pyinstrument_cext-0.2.4.dist-info/WHEEL
pyinstrument_cext-0.2.4.dist-info/RECORD
